Metadata-Version: 2.1
Name: llvm-demangle
Version: 0.0.1
Summary: Python wrapper arround llvm::demangle.
Home-page: https://github.com/MNayer/llvmdemangle
Author: MNayer
Author-email: marie.nayer@web.de
License: 0BSD
Keywords: demangling c++ cxx cpp
Platform: UNKNOWN
License-File: LICENSE.txt
